{
    "configurations": [
        {
            "name": "Mac",
            "includePath": [
                "${workspaceFolder}/**",
                "${workspaceFolder}/vendor/imgui",
                "${workspaceFolder}/vendor/assimp/include",
                "${workspaceFolder}/vendor/json",
                "/Users/lukaovsenjak/Downloads/glad/include",
                "/usr/local/include"
            ],
            "macFrameworkPath": [
                "/Applications/Xcode.app/Contents/Developer/Platforms/MacOSX.platform/Developer/SDKs/MacOSX.sdk/System/Library/Frameworks"
            ],
            "compilerPath": "/usr/bin/clang++",
            "cStandard": "c17",
            "cppStandard": "c++17",
            "intelliSenseMode": "macos-clang-x64"
        }
    ],
    "version": 4
} 